rsdclient/__init__.py
rsdclient/common/__init__.py
rsdclient/common/base.py
rsdclient/common/command.py
rsdclient/common/utils.py
rsdclient/osc/__init__.py
rsdclient/osc/plugin.py
rsdclient/osc/v2/__init__.py
rsdclient/osc/v2/fabric.py
rsdclient/osc/v2/node.py
rsdclient/osc/v2/root.py
rsdclient/osc/v2/storage_service.py
rsdclient/osc/v2/system.py
rsdclient/tests/__init__.py
rsdclient/tests/base.py
rsdclient/tests/common/__init__.py
rsdclient/tests/common/fakes.py
rsdclient/tests/common/test_command.py
rsdclient/tests/common/test_utils.py
rsdclient/tests/v2/__init__.py
rsdclient/tests/v2/test_client.py
rsdclient/tests/v2/test_fabric.py
rsdclient/tests/v2/test_node.py
rsdclient/tests/v2/test_storage_service.py
rsdclient/v2/__init__.py
rsdclient/v2/client.py
rsdclient/v2/fabric.py
rsdclient/v2/node.py
rsdclient/v2/root.py
rsdclient/v2/storage_service.py
rsdclient/v2/system.py
python_rsdclient-1.0.2.dist-info/AUTHORS
python_rsdclient-1.0.2.dist-info/LICENSE
python_rsdclient-1.0.2.dist-info/METADATA
python_rsdclient-1.0.2.dist-info/WHEEL
python_rsdclient-1.0.2.dist-info/entry_points.txt
python_rsdclient-1.0.2.dist-info/pbr.json
python_rsdclient-1.0.2.dist-info/top_level.txt
python_rsdclient-1.0.2.dist-info/RECORD
