Metadata-Version: 2.1
Name: python-rsdclient
Version: 1.0.2
Summary: OpenStack client plugin for Rack Scale Design
Home-page: https://git.openstack.org/cgit/openstack/python-rsdclient
Author: OpenStack
Author-email: openstack-discuss@lists.openstack.org
License: UNKNOWN
Platform: UNKNOWN
Classifier: Environment :: OpenStack
Classifier: Intended Audience :: Information Technology
Classifier: Intended Audience :: System Administrators
Classifier: License :: OSI Approved :: Apache Software License
Classifier: Operating System :: POSIX :: Linux
Classifier: Programming Language :: Python
Classifier: Programming Language :: Python :: 2
Classifier: Programming Language :: Python :: 2.7
Classifier: Programming Language :: Python :: 3
Classifier: Programming Language :: Python :: 3.5
Classifier: Programming Language :: Python :: 3.6
Requires-Dist: pbr (>=2.0)
Requires-Dist: osc-lib (>=1.7.0)
Requires-Dist: rsd-lib (>=1.2.0)
Requires-Dist: six (>=1.10.0)
